validation_pkg/__init__.py
validation_pkg/validation.py
validation_utils_shwemoethantx24170399-0.1.0.dist-info/licenses/LICENSE
validation_utils_shwemoethantx24170399-0.1.0.dist-info/METADATA
validation_utils_shwemoethantx24170399-0.1.0.dist-info/WHEEL
validation_utils_shwemoethantx24170399-0.1.0.dist-info/top_level.txt
validation_utils_shwemoethantx24170399-0.1.0.dist-info/RECORD
