Metadata-Version: 2.4
Name: validation-utils-shwemoethantx24170399
Version: 0.1.0
Summary: Simple validation utilities for battery levels and user roles
Home-page: https://github.com/ShweMoeThantAurum/validation-utils
Author: Shwe Moe Thant
Author-email: shwemoethant04@gmail.com
Classifier: Programming Language :: Python :: 3
Classifier: License :: OSI Approved :: MIT License
Classifier: Operating System :: OS Independent
Requires-Python: >=3.6
License-File: LICENSE
Dynamic: author
Dynamic: author-email
Dynamic: classifier
Dynamic: description-content-type
Dynamic: home-page
Dynamic: license-file
Dynamic: requires-python
Dynamic: summary
